AUTHORS.rst
CHANGES.rst
COPYING
MANIFEST.in
README.rst
setup.py
WuMapPy.egg-info/PKG-INFO
WuMapPy.egg-info/SOURCES.txt
WuMapPy.egg-info/dependency_links.txt
WuMapPy.egg-info/entry_points.txt
WuMapPy.egg-info/not-zip-safe
WuMapPy.egg-info/requires.txt
WuMapPy.egg-info/top_level.txt
docs/.gitignore
docs/Makefile
docs/about.rst
docs/changes.rst
docs/conf.py
docs/feedback.rst
docs/gen-ops.rst
docs/gen-proc.rst
docs/georef.rst
docs/gui-overview.rst
docs/index.rst
docs/install.rst
docs/mag-proc.rst
docs/make.bat
docs/quick-start.rst
docs/_static/figCorrelmapCrosscorr.png
docs/_static/figCorrelmapKendall.png
docs/_static/figCorrelmapPearson.png
docs/_static/figCorrelmapSpearman.png
docs/_static/figDataSetAnalyticSignalDlgBox.png
docs/_static/figDataSetAntiPloughingFilteringDlgBox.png
docs/_static/figDataSetConstantDestripingDlgBox.png
docs/_static/figDataSetConstantDestripingDlgBox1.png
docs/_static/figDataSetConstantDestripingDlgBox2.png
docs/_static/figDataSetConstantDestripingDlgBox3.png
docs/_static/figDataSetContinuationDlgBox.png
docs/_static/figDataSetConversionGradientMagFieldDlgBox.png
docs/_static/figDataSetCubicDestripingDlgBox.png
docs/_static/figDataSetDisplaySettingsDlgBox.png
docs/_static/figDataSetEquivStratumInMagSusceptDlgBox.png
docs/_static/figDataSetEulerDeconvolutionDlgBox.png
docs/_static/figDataSetFestoonFilteringDlgBox0.png
docs/_static/figDataSetFestoonFilteringDlgBox1.png
docs/_static/figDataSetFestoonFilteringDlgBox10.png
docs/_static/figDataSetFestoonFilteringDlgBox11.png
docs/_static/figDataSetFestoonFilteringDlgBox12.png
docs/_static/figDataSetFestoonFilteringDlgBox13.png
docs/_static/figDataSetFestoonFilteringDlgBox2.png
docs/_static/figDataSetFestoonFilteringDlgBox3.png
docs/_static/figDataSetFestoonFilteringDlgBox4.png
docs/_static/figDataSetFestoonFilteringDlgBox5.png
docs/_static/figDataSetFestoonFilteringDlgBox6.png
docs/_static/figDataSetFestoonFilteringDlgBox7.png
docs/_static/figDataSetFestoonFilteringDlgBox8.png
docs/_static/figDataSetFestoonFilteringDlgBox9.png
docs/_static/figDataSetGeoRefDlgBox.png
docs/_static/figDataSetGeoReferencingMenu.png
docs/_static/figDataSetInfo.png
docs/_static/figDataSetLogTransformationDlgBox.png
